guilded_user/__init__.py
guilded_user/client.py
guilded_user/constants.py
guilded_user-0.0.1.dist-info/METADATA
guilded_user-0.0.1.dist-info/WHEEL
guilded_user-0.0.1.dist-info/top_level.txt
guilded_user-0.0.1.dist-info/RECORD
